linear_api/__init__.py
linear_api/client.py
linear_api/explore_schema.py
linear_api/schema_validator.py
linear_api/domain/__init__.py
linear_api/domain/base_domain.py
linear_api/domain/common_models.py
linear_api/domain/enums.py
linear_api/domain/issue_models.py
linear_api/domain/project_models.py
linear_api/domain/team_models.py
linear_api/domain/user_models.py
linear_api/managers/__init__.py
linear_api/managers/base_manager.py
linear_api/managers/cache_manager.py
linear_api/managers/issue_manager.py
linear_api/managers/project_manager.py
linear_api/managers/team_manager.py
linear_api/managers/user_manager.py
linear_api/utils/__init__.py
linear_api/utils/api.py
linear_api/utils/enrichment.py
linear_api/utils/introspection_helper.py
linear_api/utils/issue_processor.py
linear_api/utils/project_processor.py
linear_api-0.2.0.dist-info/licenses/LICENSE
linear_api-0.2.0.dist-info/METADATA
linear_api-0.2.0.dist-info/WHEEL
linear_api-0.2.0.dist-info/top_level.txt
linear_api-0.2.0.dist-info/RECORD
