Metadata-Version: 2.4
Name: linear-api
Version: 0.2.0
Summary: A set of Python utilities for calling the Linear API
Home-page: https://github.com/ShoggothAI/linear-api
Author: Motley Stories AG
Author-email: egor@motley.ai
Project-URL: Bug Tracker, https://github.com/ShoggothAI/linear-api/issues
Classifier: Programming Language :: Python :: 3
Classifier: License :: OSI Approved :: MIT License
Classifier: Operating System :: OS Independent
Requires-Python: >=3.9
License-File: LICENSE
Requires-Dist: pydantic>=2.0.0
Requires-Dist: requests>=2.25.0
Dynamic: author
Dynamic: author-email
Dynamic: classifier
Dynamic: description
Dynamic: description-content-type
Dynamic: home-page
Dynamic: license-file
Dynamic: project-url
Dynamic: requires-dist
Dynamic: requires-python
Dynamic: summary
